alwhatsapp/__init__.py
alwhatsapp/whatsapp_client.py
alwhatsapp-0.5.dist-info/LICENSE.txt
alwhatsapp-0.5.dist-info/METADATA
alwhatsapp-0.5.dist-info/WHEEL
alwhatsapp-0.5.dist-info/top_level.txt
alwhatsapp-0.5.dist-info/RECORD
