Metadata-Version: 2.1
Name: alwhatsapp
Version: 0.5
Summary: Provides a WhatsApp Notification client supports Meta templates and custom messages and forms part of the AL Notificaiton Modules Suite. This version includes integration with Whapi Tool (https://panel.whapi.cloud/) to support sending to Whatsapp Groups.
Home-page: https://al.co.za/
Author: Autumn Leaf IT South Africa
Author-email: jason@al.co.za
Classifier: Programming Language :: Python :: 3
Classifier: License :: OSI Approved :: MIT License
Classifier: Operating System :: OS Independent
Requires: requests
Requires: json
License-File: LICENSE.txt
